Metadata-Version: 2.4
Name: cellfinder
Version: 1.8.0
Summary: Automated 3D cell detection in large microscopy images
Author-email: "Adam Tyson, Christian Niedworok, Charly Rousseau" <code@adamltyson.com>
License: BSD-3-Clause
Project-URL: Homepage, https://brainglobe.info/documentation/cellfinder/index.html
Project-URL: Source Code, https://github.com/brainglobe/cellfinder
Project-URL: Bug Tracker, https://github.com/brainglobe/cellfinder/issues
Project-URL: Documentation, https://brainglobe.info/documentation/cellfinder/index.html
Project-URL: User Support, https://forum.image.sc/tag/brainglobe
Classifier: Development Status :: 4 - Beta
Classifier: Framework :: napari
Classifier: Intended Audience :: Developers
Classifier: Intended Audience :: Science/Research
Classifier: Operating System :: OS Independent
Classifier: Programming Language :: Python
Classifier: Programming Language :: Python :: 3
Classifier: Programming Language :: Python :: 3.11
Classifier: Programming Language :: Python :: 3.12
Classifier: Programming Language :: Python :: 3.13
Classifier: Topic :: Scientific/Engineering :: Image Recognition
Requires-Python: >=3.11
License-File: LICENSE
Requires-Dist: brainglobe-utils>=0.5.0
Requires-Dist: brainglobe-napari-io>=0.3.4
Requires-Dist: dask[array]
Requires-Dist: fancylog>=0.0.7
Requires-Dist: natsort
Requires-Dist: numba
Requires-Dist: numpy
Requires-Dist: scikit-image
Requires-Dist: scikit-learn
Requires-Dist: keras>=3.7.0
Requires-Dist: torch>=2.4.1
Requires-Dist: tifffile
Requires-Dist: tqdm
Requires-Dist: qt-niu
Provides-Extra: dev
Requires-Dist: black; extra == "dev"
Requires-Dist: pre-commit; extra == "dev"
Requires-Dist: pyinstrument; extra == "dev"
Requires-Dist: pytest-cov; extra == "dev"
Requires-Dist: pytest-mock; extra == "dev"
Requires-Dist: pytest-qt; extra == "dev"
Requires-Dist: pytest-timeout; extra == "dev"
Requires-Dist: pytest; extra == "dev"
Requires-Dist: tox; extra == "dev"
Requires-Dist: pooch>=1; extra == "dev"
Provides-Extra: napari
Requires-Dist: brainglobe-napari-io; extra == "napari"
Requires-Dist: magicgui; extra == "napari"
Requires-Dist: napari-ndtiffs; extra == "napari"
Requires-Dist: napari-plugin-engine>=0.1.4; extra == "napari"
Requires-Dist: napari[pyqt5]>=0.6.1; extra == "napari"
Requires-Dist: pooch>=1; extra == "napari"
Requires-Dist: qtpy; extra == "napari"
Dynamic: license-file
